{"data":{"site":{"siteMetadata":{"title":"luetkemj","description":"Change Is Good","author":"mark luetke"}},"markdownRemark":{"excerpt":"Finally got a monitor for the raspberry pi. Spent the evening getting some basic things setup. Github has it's muck all set up with SSH and…","html":"<p>Finally got a monitor for the raspberry pi. Spent the evening getting some basic things setup. Github has it's muck all set up with SSH and what not. I got nvm and rvm up and running. No jvm yet but we'll see if we even need it.</p>\n<p>Jekyll is being a butt so I'm hoping this works on github when I push. It should I think... but we'll find out I suppose.</p>\n<p>I'm writing this in VI which is super weird for me. I keep trying to use the arrow keys and VI really doesn't like it. Trying hard to break old habits even if only temporarily.</p>\n<p>Sure does get late quick...</p>\n<p>Time to kick it soon.</p>\n<p>*edited in atom on my mac later - yes I cheated a but I suppose...</p>","frontmatter":{"date":"160423","title":"VI in pi","illustration":null,"layout":"post"}},"allFile":{"edges":[{"node":{"relativePath":"forest-gump.jpg","publicURL":"/static/forest-gump-cb60a493d812bb1e574418382f053dce.jpg"}},{"node":{"relativePath":"luetkemj.png","publicURL":"/static/luetkemj-1831991e0e0c9cc03aa10eca078afa54.png"}},{"node":{"relativePath":"neistat.png","publicURL":"/static/neistat-ef667e42ff76189bfb9374db77d8a5f3.png"}},{"node":{"relativePath":"CA-190805-PO5.png","publicURL":"/static/CA-190805-PO5-8f4d2c8fdad23dd34a37a5a78ead1ad1.png"}},{"node":{"relativePath":"CA-190805-ball-spinning.gif","publicURL":"/static/CA-190805-ball-spinning-584cbc3260dd8d37d2dc4d57d4fe15ea.gif"}},{"node":{"relativePath":"CA-190805-ball-bouncing.gif","publicURL":"/static/CA-190805-ball-bouncing-08773357003ecdc0ca6243769528e2c1.gif"}},{"node":{"relativePath":"CA-190805-double-take.gif","publicURL":"/static/CA-190805-double-take-7c966447b035acc49491fbdcdb6a30b4.gif"}},{"node":{"relativePath":"CA-190805-walks.gif","publicURL":"/static/CA-190805-walks-b81a25df3b9c73ec6bb0a083f0d940c2.gif"}},{"node":{"relativePath":"CA-190722-cerebral-flab.png","publicURL":"/static/CA-190722-cerebral-flab-00a3862364464b2078d0f518fd91e8b9.png"}},{"node":{"relativePath":"CA-190814-old-horse-thief.jpg","publicURL":"/static/CA-190814-old-horse-thief-bc1775f77b23d060fa622f87468886c1.jpg"}},{"node":{"relativePath":"CA-190902-aglet.png","publicURL":"/static/CA-190902-aglet-95fc03afbf4429a0ca2ebba900ee8759.png"}},{"node":{"relativePath":"CA-191117-snerv.png","publicURL":"/static/CA-191117-snerv-653428e39f54328fd5fda9da4a58dc0d.png"}},{"node":{"relativePath":"CA-191117-how-to-make-a-roguelike.png","publicURL":"/static/CA-191117-how-to-make-a-roguelike-8ac6b5eb72dc309e8ed002abc5babc91.png"}},{"node":{"relativePath":"CA-191117-snail.png","publicURL":"/static/CA-191117-snail-a46b03fed45b55d545309a400d9f0d10.png"}},{"node":{"relativePath":"CA-191117-rltut.png","publicURL":"/static/CA-191117-rltut-ded16b0723e9b5d6e17f0cdaaa4f8f4f.png"}},{"node":{"relativePath":"CA-191117-snail2.png","publicURL":"/static/CA-191117-snail2-e0c8b4f93b470dd33861498f8d5c1b04.png"}},{"node":{"relativePath":"CA-191117-pcgdgns.gif","publicURL":"/static/CA-191117-pcgdgns-c9e6f7584599b5587a82d55e3cdc6c91.gif"}}]},"nextPost":{"edges":[{"node":{"path":"/160421/random-body-parts-chart"}}]},"nextPostMarkdown":{"frontmatter":{"title":"Random Body Parts Chart"}},"previousPost":{"edges":[{"node":{"path":"/160424/goblin-inspired-gear"}}]},"previousPostMarkdown":{"frontmatter":{"title":"Goblin Inspired Gear"}}},"pageContext":{"nextPostPath":"/160421/random-body-parts-chart","previousPostPath":"/160424/goblin-inspired-gear"}}