{"data":{"site":{"siteMetadata":{"title":"luetkemj","description":"Change Is Good","author":"mark luetke"}},"markdownRemark":{"excerpt":"In this ever evolving quest that is scribe I am doing some initial exploration into  PixiJS . It’s a super fast 2d graphics rendering…","html":"<p>In this ever evolving quest that is scribe I am doing some initial exploration into <a href=\"http://www.pixijs.com/\">PixiJS</a>. It’s a super fast 2d graphics rendering renderer. It’s also a completely different world for me and I know very littel about it. This has the potential to open a lot of doors. Just have to invest a bit of time into it first. A very long tutorial and docs await me on either a late night or early morning. Morning with coffee sounds much better 🌄☕😀</p>\n<p>And look, a sprite!</p>\n<p data-height=\"290\" data-theme-id=\"0\" data-slug-hash=\"QveYwV\" data-default-tab=\"result\" data-user=\"luetkemj\" data-embed-version=\"2\" data-pen-title=\"QveYwV\" class=\"codepen\">See the Pen <a href=\"https://codepen.io/luetkemj/pen/QveYwV/\">QveYwV</a> by Mark Luetke (<a href=\"https://codepen.io/luetkemj\">@luetkemj</a>) on <a href=\"https://codepen.io\">CodePen</a>.</p>\n<script async src=\"https://production-assets.codepen.io/assets/embed/ei.js\"></script>","frontmatter":{"date":"170531","title":"PixiJS","illustration":null,"layout":"post"}},"allFile":{"edges":[{"node":{"relativePath":"forest-gump.jpg","publicURL":"/static/forest-gump-cb60a493d812bb1e574418382f053dce.jpg"}},{"node":{"relativePath":"luetkemj.png","publicURL":"/static/luetkemj-1831991e0e0c9cc03aa10eca078afa54.png"}},{"node":{"relativePath":"neistat.png","publicURL":"/static/neistat-ef667e42ff76189bfb9374db77d8a5f3.png"}},{"node":{"relativePath":"CA-190805-PO5.png","publicURL":"/static/CA-190805-PO5-8f4d2c8fdad23dd34a37a5a78ead1ad1.png"}},{"node":{"relativePath":"CA-190805-ball-spinning.gif","publicURL":"/static/CA-190805-ball-spinning-584cbc3260dd8d37d2dc4d57d4fe15ea.gif"}},{"node":{"relativePath":"CA-190805-ball-bouncing.gif","publicURL":"/static/CA-190805-ball-bouncing-08773357003ecdc0ca6243769528e2c1.gif"}},{"node":{"relativePath":"CA-190805-double-take.gif","publicURL":"/static/CA-190805-double-take-7c966447b035acc49491fbdcdb6a30b4.gif"}},{"node":{"relativePath":"CA-190805-walks.gif","publicURL":"/static/CA-190805-walks-b81a25df3b9c73ec6bb0a083f0d940c2.gif"}},{"node":{"relativePath":"CA-190722-cerebral-flab.png","publicURL":"/static/CA-190722-cerebral-flab-00a3862364464b2078d0f518fd91e8b9.png"}},{"node":{"relativePath":"CA-190814-old-horse-thief.jpg","publicURL":"/static/CA-190814-old-horse-thief-bc1775f77b23d060fa622f87468886c1.jpg"}},{"node":{"relativePath":"CA-190814-old-horse-thief-running.jpg","publicURL":"/static/CA-190814-old-horse-thief-running-373d1c05c9f98cdbb581c2fd60ef87c8.jpg"}}]},"nextPost":{"edges":[{"node":{"path":"/170530/flow"}}]},"nextPostMarkdown":{"frontmatter":{"title":"Flow"}},"previousPost":{"edges":[{"node":{"path":"/170610/what-I-think-about-when-I-think-about-writing-about-writing-code"}}]},"previousPostMarkdown":{"frontmatter":{"title":"What I think about when I think about writing about writing code"}}},"pageContext":{"nextPostPath":"/170530/flow","previousPostPath":"/170610/what-I-think-about-when-I-think-about-writing-about-writing-code"}}